ampycloud/__init__.py
ampycloud/__main__.py
ampycloud/cluster.py
ampycloud/core.py
ampycloud/data.py
ampycloud/dynamic.py
ampycloud/errors.py
ampycloud/fluffer.py
ampycloud/hardcoded.py
ampycloud/icao.py
ampycloud/layer.py
ampycloud/logger.py
ampycloud/scaler.py
ampycloud/version.py
ampycloud/wmo.py
ampycloud/plots/__init__.py
ampycloud/plots/core.py
ampycloud/plots/diagnostics.py
ampycloud/plots/hardcoded.py
ampycloud/plots/secondary.py
ampycloud/plots/tools.py
ampycloud/plots/mpl_styles/base.mplstyle
ampycloud/plots/mpl_styles/latex.mplstyle
ampycloud/plots/mpl_styles/metsymb.mplstyle
ampycloud/prms/ampycloud_default_prms.yml
ampycloud/utils/__init__.py
ampycloud/utils/mocker.py
ampycloud/utils/performance.py
ampycloud/utils/utils.py
ampycloud-2.1.1.dist-info/LICENSE
ampycloud-2.1.1.dist-info/METADATA
ampycloud-2.1.1.dist-info/WHEEL
ampycloud-2.1.1.dist-info/entry_points.txt
ampycloud-2.1.1.dist-info/top_level.txt
ampycloud-2.1.1.dist-info/RECORD
