Metadata-Version: 2.1
Name: ampycloud
Version: 2.1.1
Summary: Determining the sky coverage fraction and base height of cloud layers usingceilometer data
Home-page: https://meteoswiss.github.io/ampycloud
Author: Frédéric P.A. Vogt, Daniel Regenass
Author-email: frederic.vogt@meteoswiss.ch
License: BSD-3-Clause
Project-URL: Source, https://github.com/MeteoSwiss/ampycloud/
Project-URL: Changelog, https://meteoswiss.github.io/ampycloud/changelog.html
Project-URL: Issues, https://github.com/MeteoSwiss/ampycloud/issues
Classifier: Development Status :: 5 - Production/Stable
Classifier: Intended Audience :: Science/Research
Classifier: Topic :: Scientific/Engineering :: Atmospheric Science
Classifier: License :: OSI Approved :: BSD License
Classifier: Programming Language :: Python
Classifier: Programming Language :: Python :: 3.9
Classifier: Programming Language :: Python :: 3.10
Classifier: Programming Language :: Python :: 3.11
Requires-Python: >=3.9.0
License-File: LICENSE
Requires-Dist: matplotlib>=3.7.2
Requires-Dist: numpy>=1.20.3
Requires-Dist: scikit-learn>=1.2.0
Requires-Dist: scipy>=1.7.3
Requires-Dist: statsmodels>=0.14.3
Requires-Dist: pandas>=1.5
Requires-Dist: pyyaml
Requires-Dist: ruamel.yaml
Provides-Extra: dev
Requires-Dist: sphinx; extra == "dev"
Requires-Dist: sphinx-rtd-theme; extra == "dev"
Requires-Dist: pylint; extra == "dev"
Requires-Dist: pytest; extra == "dev"
Requires-Dist: setuptools; extra == "dev"
Requires-Dist: mypy; extra == "dev"
